sphinx_book_theme/__init__.py
sphinx_book_theme/_compile_translations.py
sphinx_book_theme/_transforms.py
sphinx_book_theme/assets/scripts/index.js
sphinx_book_theme/assets/styles/abstracts/_mixins.scss
sphinx_book_theme/assets/styles/abstracts/_variables.scss
sphinx_book_theme/assets/styles/base/_base.scss
sphinx_book_theme/assets/styles/base/_print.scss
sphinx_book_theme/assets/styles/base/_typography.scss
sphinx_book_theme/assets/styles/components/_back-to-top.scss
sphinx_book_theme/assets/styles/components/_icon-links.scss
sphinx_book_theme/assets/styles/components/_logo.scss
sphinx_book_theme/assets/styles/components/_search.scss
sphinx_book_theme/assets/styles/content/_code.scss
sphinx_book_theme/assets/styles/content/_images.scss
sphinx_book_theme/assets/styles/content/_margin.scss
sphinx_book_theme/assets/styles/content/_notebooks.scss
sphinx_book_theme/assets/styles/content/_quotes.scss
sphinx_book_theme/assets/styles/extensions/_comments.scss
sphinx_book_theme/assets/styles/extensions/_thebe.scss
sphinx_book_theme/assets/styles/index.scss
sphinx_book_theme/assets/styles/sections/_announcement.scss
sphinx_book_theme/assets/styles/sections/_article-container.scss
sphinx_book_theme/assets/styles/sections/_article.scss
sphinx_book_theme/assets/styles/sections/_footer-article.scss
sphinx_book_theme/assets/styles/sections/_footer-content.scss
sphinx_book_theme/assets/styles/sections/_header-article.scss
sphinx_book_theme/assets/styles/sections/_header-primary.scss
sphinx_book_theme/assets/styles/sections/_sidebar-primary.scss
sphinx_book_theme/assets/styles/sections/_sidebar-secondary.scss
sphinx_book_theme/assets/translations/README.md
sphinx_book_theme/assets/translations/jsons/By the.json
sphinx_book_theme/assets/translations/jsons/By.json
sphinx_book_theme/assets/translations/jsons/Contents.json
sphinx_book_theme/assets/translations/jsons/Copyright.json
sphinx_book_theme/assets/translations/jsons/Download notebook file.json
sphinx_book_theme-1.1.1.dist-info/LICENSE
sphinx_book_theme-1.1.1.dist-info/METADATA
sphinx_book_theme-1.1.1.dist-info/WHEEL
sphinx_book_theme-1.1.1.dist-info/entry_points.txt
sphinx_book_theme-1.1.1.dist-info/RECORD