Metadata-Version: 2.1
Name: sphinx-book-theme
Version: 1.1.1
Summary: A clean book theme for scientific explanations and documentation with Sphinx
Maintainer-Email: Executable Books Team <executablebooks@gmail.com>
License: BSD 3-Clause License
Classifier: Development Status :: 4 - Beta
Classifier: Programming Language :: Python :: 3
Classifier: Framework :: Sphinx
Classifier: Framework :: Sphinx :: Theme
Classifier: License :: OSI Approved :: BSD License
Classifier: Operating System :: OS Independent
Project-URL: Repository, https://github.com/executablebooks/sphinx-book-theme
Project-URL: Documentation, https://sphinx-book-theme.readthedocs.io/
Requires-Python: >=3.9
Requires-Dist: sphinx>=5
Requires-Dist: pydata-sphinx-theme>=0.14
Requires-Dist: pre-commit; extra == "code-style"
Requires-Dist: ablog; extra == "doc"
Requires-Dist: ipywidgets; extra == "doc"
Requires-Dist: folium; extra == "doc"
Requires-Dist: numpy; extra == "doc"
Requires-Dist: matplotlib; extra == "doc"
Requires-Dist: numpydoc; extra == "doc"
Requires-Dist: myst-nb; extra == "doc"
Requires-Dist: nbclient; extra == "doc"
Requires-Dist: pandas; extra == "doc"
Requires-Dist: plotly; extra == "doc"
Requires-Dist: sphinx-design; extra == "doc"
Requires-Dist: sphinx-examples; extra == "doc"
Requires-Dist: sphinx-copybutton; extra == "doc"
Requires-Dist: sphinx-tabs; extra == "doc"
Requires-Dist: sphinx-togglebutton; extra == "doc"
Requires-Dist: sphinx-thebe; extra == "doc"
Requires-Dist: sphinxcontrib-bibtex; extra == "doc"
Requires-Dist: sphinxcontrib-youtube; extra == "doc"
Requires-Dist: sphinxext-opengraph; extra == "doc"
Requires-Dist: beautifulsoup4; extra == "test"
Requires-Dist: coverage; extra == "test"
Requires-Dist: myst-nb; extra == "test"
Requires-Dist: pytest; extra == "test"
Requires-Dist: pytest-cov; extra == "test"
Requires-Dist: pytest-regressions; extra == "test"
Requires-Dist: sphinx_thebe; extra == "test"
Provides-Extra: code_style
Provides-Extra: doc
Provides-Extra: test
